bra_loterias/__init__.py
bra_loterias/cli.py
bra_loterias/loteria.py
bra_loterias-0.1.0.dist-info/LICENSE
bra_loterias-0.1.0.dist-info/entry_points.txt
bra_loterias-0.1.0.dist-info/WHEEL
bra_loterias-0.1.0.dist-info/METADATA
bra_loterias-0.1.0.dist-info/RECORD
