Metadata-Version: 2.1
Name: bra-loterias
Version: 0.1.0
Summary: Bra loterias é um CLI para coletar resultados, conferir e gerar jogos das loterias CAIXA. Projeto com finalidades educacionais
License: MIT
Author: Johann Philipi
Author-email: joliveira.info@gmail.com
Requires-Python: >=3.11,<4.0
Classifier: Development Status :: 5 - Production/Stable
Classifier: Environment :: Console
Classifier: License :: OSI Approved :: MIT License
Classifier: Natural Language :: Portuguese (Brazilian)
Classifier: Programming Language :: Python :: 3
Classifier: Programming Language :: Python :: 3.11
Classifier: Programming Language :: Python :: 3.11
Classifier: Topic :: Education
Requires-Dist: beautifulsoup4 (>=4.12.2,<5.0.0)
Requires-Dist: pydantic (>=1.10.7,<2.0.0)
Requires-Dist: rich (>=13.3.4,<14.0.0)
Requires-Dist: typer (>=0.7.0,<0.8.0)
Project-URL: Bug Tracker, https://github.com/JohannPhilipi/bra-loterias/issues
Project-URL: Código, https://github.com/JohannPhilipi/bra-loterias
Project-URL: Documentação, https://bra-loterias.readthedocs.io/en/latest/
